wordllama/RESULTS.md
wordllama/__init__.py
wordllama/_version.py
wordllama/inference.py
wordllama/mode_decorators.py
wordllama/wordllama.py
wordllama/adapters/__init__.py
wordllama/adapters/avg_pool.py
wordllama/adapters/binarizer.py
wordllama/adapters/mlp.py
wordllama/adapters/projector.py
wordllama/adapters/weighted_mlp.py
wordllama/adapters/weighted_projector.py
wordllama/algorithms/__init__.py
wordllama/algorithms/deduplicate_helpers.c
wordllama/algorithms/deduplicate_helpers.cp311-win_amd64.pyd
wordllama/algorithms/deduplicate_helpers.pyx
wordllama/algorithms/find_local_minima.cp311-win_amd64.pyd
wordllama/algorithms/find_local_minima.cpp
wordllama/algorithms/find_local_minima.pyx
wordllama/algorithms/kmeans.c
wordllama/algorithms/kmeans.cp311-win_amd64.pyd
wordllama/algorithms/kmeans.pyx
wordllama/algorithms/semantic_splitter.py
wordllama/algorithms/splitter.cp311-win_amd64.pyd
wordllama/algorithms/splitter.cpp
wordllama/algorithms/splitter.pyx
wordllama/algorithms/vector_similarity.c
wordllama/algorithms/vector_similarity.cp311-win_amd64.pyd
wordllama/algorithms/vector_similarity.pxd
wordllama/algorithms/vector_similarity.pyx
wordllama/config/__init__.py
wordllama/config/models.py
wordllama/config/train/command_rplus.toml
wordllama/config/train/dbrx.toml
wordllama/config/train/deberta_v3_large.toml
wordllama/config/train/deepseekv2.toml
wordllama/config/train/gemma2_27B.toml
wordllama/config/train/l2_supercat.toml
wordllama/config/train/l2p3.toml
wordllama/config/train/l2p3_lg.toml
wordllama/config/train/l3_supercat.toml
wordllama/config/train/llama2_70B.toml
wordllama/config/train/llama3_70B.toml
wordllama/config/train/llama3_8B.toml
wordllama/config/train/llamaguard.toml
wordllama/config/train/miqu.toml
wordllama/config/train/mixtral.toml
wordllama/config/train/mixtral_8x22B.toml
wordllama/config/train/openelm_3B.toml
wordllama/config/train/phi3_medium.toml
wordllama/config/train/qwen2_72B.toml
wordllama/config/train/yi_1v5_34B.toml
wordllama-0.3.9.dist-info/LICENSE
wordllama-0.3.9.dist-info/METADATA
wordllama-0.3.9.dist-info/WHEEL
wordllama-0.3.9.dist-info/top_level.txt
wordllama-0.3.9.dist-info/RECORD
