Metadata-Version: 2.2
Name: wordllama
Version: 0.3.9
Summary: WordLlama NLP Utility
Author-email: Lee Miller <dleemiller@gmail.com>
License: MIT License
Project-URL: Homepage, https://github.com/dleemiller
Project-URL: Repository, https://github.com/dleemiller/WordLlama
Requires-Python: >=3.8
License-File: LICENSE
Requires-Dist: numpy>=2
Requires-Dist: safetensors
Requires-Dist: tokenizers
Requires-Dist: toml
Requires-Dist: pydantic>=2
Requires-Dist: requests
Provides-Extra: train
Requires-Dist: accelerate; extra == "train"
Requires-Dist: torch>=2; extra == "train"
Requires-Dist: transformers>=4; extra == "train"
Requires-Dist: sentence-transformers; extra == "train"
Requires-Dist: datasets; extra == "train"
Requires-Dist: nltk; extra == "train"
